dotsync_fast/__init__.py
dotsync_fast/cli.py
dotsync_fast-0.2.0.dist-info/METADATA
dotsync_fast-0.2.0.dist-info/WHEEL
dotsync_fast-0.2.0.dist-info/entry_points.txt
dotsync_fast-0.2.0.dist-info/RECORD
