Metadata-Version: 2.1
Name: dotsync_fast
Version: 0.2.0
Summary: The last dotfile syncer you'll ever need.
Author: Hunter Gatewood
Author-email: hgatewood@gmail.com
Requires-Python: >=3.12,<4.0
Classifier: Programming Language :: Python :: 3
Classifier: Programming Language :: Python :: 3.12
Requires-Dist: click (>=8.0.0,<9.0.0)
Requires-Dist: click_aliases (>=1.0.5,<2.0.0)
Requires-Dist: click_default_group (>=1.2.4,<2.0.0)
Requires-Dist: hcgatewood_coda (>=1.0.0,<2.0.0)
Requires-Dist: jinja2 (>=3.1.6,<4.0.0)
Requires-Dist: pydantic (>=2.12.0,<3.0.0)
Requires-Dist: pyyaml (>=6.0,<7.0)
Requires-Dist: watchfiles (>=1.1.1,<2.0.0)
